setup.cfg
setup.py
notion_adapt/__init__.py
notion_adapt/block.py
notion_adapt/client.py
notion_adapt/collection.py
notion_adapt/logger.py
notion_adapt/maps.py
notion_adapt/markdown.py
notion_adapt/monitor.py
notion_adapt/operations.py
notion_adapt/records.py
notion_adapt/settings.py
notion_adapt/smoke_test.py
notion_adapt/space.py
notion_adapt/store.py
notion_adapt/user.py
notion_adapt/utils.py
notion_adapt.egg-info/PKG-INFO
notion_adapt.egg-info/SOURCES.txt
notion_adapt.egg-info/dependency_links.txt
notion_adapt.egg-info/requires.txt
notion_adapt.egg-info/top_level.txt