Metadata-Version: 1.0
Name: notion-adapt
Version: 0.0.1
Summary: notion-py with auto multiselect tage creation
Home-page: UNKNOWN
Author: uzapolsky
Author-email: uzapolsky@gmail.com
License: UNKNOWN
Platform: UNKNOWN
